<annotation>
	<folder>Frames</folder>
	<filename>Peace153.jpg</filename>
	<path>U:\Documents\Proyectos\Wink\Addons\Frames\Peace153.jpg</path>
	<source>
		<database>Unknown</database>
	</source>
	<size>
		<width>800</width>
		<height>600</height>
		<depth>3</depth>
	</size>
	<segmented>0</segmented>
	<object>
		<name>Peace</name>
		<pose>Unspecified</pose>
		<truncated>0</truncated>
		<difficult>0</difficult>
		<bndbox>
			<xmin>387</xmin>
			<ymin>125</ymin>
			<xmax>577</xmax>
			<ymax>484</ymax>
		</bndbox>
	</object>
</annotation>
