<annotation>
	<folder>Frames</folder>
	<filename>PeaceL94.jpg</filename>
	<path>U:\Documents\Proyectos\Wink\Addons\Frames\PeaceL94.jpg</path>
	<source>
		<database>Unknown</database>
	</source>
	<size>
		<width>1920</width>
		<height>1080</height>
		<depth>3</depth>
	</size>
	<segmented>0</segmented>
	<object>
		<name>Peace</name>
		<pose>Unspecified</pose>
		<truncated>0</truncated>
		<difficult>0</difficult>
		<bndbox>
			<xmin>835</xmin>
			<ymin>429</ymin>
			<xmax>1148</xmax>
			<ymax>984</ymax>
		</bndbox>
	</object>
</annotation>
