<annotation>
	<folder>Frames</folder>
	<filename>OkL188.jpg</filename>
	<path>U:\Documents\Proyectos\Wink\Addons\Frames\OkL188.jpg</path>
	<source>
		<database>Unknown</database>
	</source>
	<size>
		<width>1920</width>
		<height>1080</height>
		<depth>3</depth>
	</size>
	<segmented>0</segmented>
	<object>
		<name>Ok</name>
		<pose>Unspecified</pose>
		<truncated>0</truncated>
		<difficult>0</difficult>
		<bndbox>
			<xmin>1345</xmin>
			<ymin>258</ymin>
			<xmax>1615</xmax>
			<ymax>696</ymax>
		</bndbox>
	</object>
</annotation>
